django_auth_tacacs/__init__.py
django_auth_tacacs/django.py
django_auth_tacacs/nautobot.py
django_auth_tacacs/netbox.py
django_auth_tacacs-0.0.1.dist-info/LICENSE
django_auth_tacacs-0.0.1.dist-info/METADATA
django_auth_tacacs-0.0.1.dist-info/WHEEL
django_auth_tacacs-0.0.1.dist-info/RECORD
