Metadata-Version: 2.1
Name: django-auth-tacacs
Version: 0.0.1
Summary: Tacacs+ external authentication backend for Django - Nautbot - Netbox
License: LICENSE
Author: Maarten Wallraf
Author-email: mwallraf@2nms.com
Requires-Python: >=3.8.1
Classifier: License :: Other/Proprietary License
Classifier: Programming Language :: Python :: 3
Classifier: Programming Language :: Python :: 3.9
Classifier: Programming Language :: Python :: 3.10
Classifier: Programming Language :: Python :: 3.11
Requires-Dist: tacacs_plus (>=2.6,<3.0)
